pipxu/__init__.py
pipxu/__main__.py
pipxu/pipxu.py
pipxu/run.py
pipxu/utils.py
pipxu/commands/debug.py
pipxu/commands/inject.py
pipxu/commands/install.py
pipxu/commands/list.py
pipxu/commands/reinstall.py
pipxu/commands/runpip.py
pipxu/commands/uninject.py
pipxu/commands/uninstall.py
pipxu/commands/upgrade.py
pipxu/commands/venv.py
pipxu/commands/version.py
pipxu-1.33.data/scripts/pipxu-bootstrap
pipxu-1.33.dist-info/METADATA
pipxu-1.33.dist-info/WHEEL
pipxu-1.33.dist-info/entry_points.txt
pipxu-1.33.dist-info/top_level.txt
pipxu-1.33.dist-info/RECORD
