Metadata-Version: 2.4
Name: pipxu
Version: 1.33
Summary: Install and Run Python Applications in Isolated Environments using UV
Author-email: Mark Blakeney <mark.blakeney@bullet-systems.net>
License-Expression: GPL-3.0-or-later
Project-URL: Homepage, https://github.com/bulletmark/pipxu
Keywords: pipx,pip,uv,venv,virtualenv
Classifier: Programming Language :: Python :: 3
Requires-Python: >=3.8
Requires-Dist: argcomplete
Requires-Dist: filelock
Requires-Dist: platformdirs
Requires-Dist: argparse-from-file
Requires-Dist: packaging
